{"0_0.0.md":"9c3d4d4a","2_2.1.md":"af34f7ac","0_0.3.md":"16450755","10_10.1.md":"0df07d7c","0_author.md":"3633c7ae","1_1.1.md":"abdeb8ec","1_1.2.md":"75259fa8","1_1.3.md":"c541d3f4","2_2.4.md":"eac02f22","10_10.4.md":"4575c123","2_2.2.md":"768d8595","10_10.3.md":"a31225d3","10_10.2.md":"7524c989","2_domainlayer.md":"f89b20c6","2_infrastructurelayer.md":"d762ead7","2_userinterfacelayer.md":"43193182","3_aggregate.md":"c19fe142","3_domainservice.md":"54efee77","3_entity.md":"a78fdb9e","3_valueobject.md":"db6034d5","4_factory.md":"a716cf36","4_repository.md":"bf194cca","5_5.1.md":"3b77c41c","5_5.4.md":"36dcef29","2_2.5.md":"d8d10679","2_2.6.md":"8bd5ee10","2_applicationlayer.md":"a0b48efb","6_domainevent1.md":"ad20ee32","6_domainevent2.md":"b1d9f729","6_domainevent3.md":"8433ceb2","6_domainevent4.md":"c5a3022f","7_7.2.md":"06f2e94c","8_consistencybetweenaggregate.md":"615182ad","6_idempotent.md":"8410623d","9_9.1.md":"c4e03399","9_9.2.md":"a3744eac","9_9.3.md":"a663ece0","strategicdesign_boundcontext.md":"454a48a2","strategicdesign_contextmap.md":"74eeb913","strategicdesign_strategicdesign.md":"1316e152","index.md":"048dd6fa","footer.md":"2b1bb7a5","7_7.1.md":"2f628499","8_consistencyinaggregate.md":"f6d0d83f","2_2.3.md":"e114445d"}
