{"0_0.0.md":"64ae9f61","2_2.3.md":"b259911d","0_author.md":"958baf11","1_1.1.md":"b1db19ff","1_1.2.md":"51fb1d95","1_1.3.md":"fd5da497","10_codegenerator.md":"9f8491c1","10_mavenarchetype.md":"19e40dae","2_2.1.md":"8ca39042","2_userinterfacelayer.md":"e7f78bb5","0_0.3.md":"8ad0d461","2_applicationlayer.md":"e7b3a1c3","2_2.4.md":"3ab72e0f","9_staticanalysis.md":"f40e5653","9_tdd.md":"a72a7b3a","strategicdesign_acl.md":"a1193f0b","strategicdesign_boundcontext.md":"367f1df8","strategicdesign_contextmap.md":"fad8d52c","2_infrastructurelayer.md":"4f1086ac","2_2.5.md":"72486284","2_2.6.md":"4d709070","2_domainlayer.md":"df2bd686","4_factory.md":"29a53817","4_repository.md":"b4b2e897","5_gofdesignpattern.md":"d8174009","5_side-effect-freefunction.md":"dfb016b9","6_domainevent2.md":"853bf783","9_codingguidelines.md":"c168aa41","6_domainevent4.md":"05dce31f","6_idempotent.md":"bb0e3aac","6_domainevent3.md":"561a481b","7_cqrs.md":"36cb2083","8_consistencyinaggregate.md":"be1f6455","8_consistencybetweenaggregate.md":"4cc4a96a","7_eventsourcing.md":"af306be4","6_domainevent1.md":"102f68d6","2_2.2.md":"948b784e","strategicdesign_subdomain.md":"66b27a45","3_entity.md":"0eb98c26","3_domainservice.md":"4f226177","3_valueobject.md":"5f235c4d","3_aggregate.md":"b2e932e5","strategicdesign_strategicdesign.md":"d228d090","footer.md":"ecee300a","index.md":"2b00a692"}
